twarc/__init__.py
twarc/__main__.py
twarc/client.py
twarc/client2.py
twarc/command.py
twarc/command2.py
twarc/config.py
twarc/decorators.py
twarc/decorators2.py
twarc/expansions.py
twarc/handshake.py
twarc/json2csv.py
twarc/version.py
twarc-2.14.0.dist-info/LICENSE
twarc-2.14.0.dist-info/METADATA
twarc-2.14.0.dist-info/WHEEL
twarc-2.14.0.dist-info/entry_points.txt
twarc-2.14.0.dist-info/top_level.txt
twarc-2.14.0.dist-info/RECORD
