Metadata-Version: 2.1
Name: twarc
Version: 2.14.0
Summary: Archive tweets from the command line
Home-page: https://github.com/docnow/twarc
Author: Ed Summers
Author-email: ehs@pobox.com
License: MIT
Platform: UNKNOWN
Classifier: License :: OSI Approved :: MIT License
Requires-Python: >=3.6
